swytchit/__init__.py
swytchit/__main__.py
swytchit/command/__init__.py
swytchit/command/start_command.py
swytchit/error.py
swytchit-0.2.1.dist-info/METADATA
swytchit-0.2.1.dist-info/WHEEL
swytchit-0.2.1.dist-info/entry_points.txt
swytchit-0.2.1.dist-info/RECORD
