Metadata-Version: 2.1
Name: swytchit
Version: 0.2.1
Summary: Switch environment context easily in the shell
Home-page: https://steamwiz.io
License: MIT
Author: Steampunk Wizard
Author-email: swytchit@steamwiz.io
Requires-Python: >=3.11,<3.12
Classifier: License :: OSI Approved :: MIT License
Classifier: Programming Language :: Python :: 3
Classifier: Programming Language :: Python :: 3.11
Requires-Dist: wizlib (>=3.1.4,<4.0.0)
Project-URL: Repository, https://gitlab.com/steamwiz/swytchit
